pymandua/__init__.py
pymandua/__main__.py
pymandua/aggregator.py
pymandua/app.py
pymandua/cleaner.py
pymandua/converter.py
pymandua/crawler.py
pymandua/driver.py
pymandua/gatherer.py
pymandua/ingest.py
pymandua/interface.py
pymandua/provider_loader.py
pymandua/query.py
pymandua/treater.py
pymandua-0.1.2.dist-info/licenses/LICENSE
pymandua-0.1.2.dist-info/METADATA
pymandua-0.1.2.dist-info/WHEEL
pymandua-0.1.2.dist-info/top_level.txt
pymandua-0.1.2.dist-info/RECORD
