Metadata-Version: 2.4
Name: pymandua
Version: 0.1.2
Summary: Uma biblioteca para scraping com lógica fuzzy e conversão de HTML e conteúdos ao seu redor, lidando com reatividade do javascript para Markdown focado em LLMs. Adicionado com um pipeline RAG.
Home-page: https://github.com/seuusuario/web-scraper-with-ai
Author: Marcos Henrique Maimoni Campanella
Author-email: "Marcos H. M. Campanella" <mhmcamp@gmail.com>
License: MIT
Project-URL: homepage, https://github.com/Mark-Campanella/pymandua
Project-URL: repository, https://github.com/Mark-Campanella/pymandua
Keywords: scraping,fuzzy logic,HTML to Markdown,JavaScript reactivity,LLM,web scraping,RAG,retrieval-augmented generation,LangChain
Classifier: Development Status :: 3 - Alpha
Classifier: Intended Audience :: Developers
Classifier: License :: OSI Approved :: MIT License
Classifier: Programming Language :: Python :: 3.11
Classifier: Operating System :: OS Independent
Classifier: Topic :: Software Development :: Libraries :: Python Modules
Requires-Python: >=3.8
License-File: LICENSE
Requires-Dist: beautifulsoup4<5.0.0,>=4.14.0
Requires-Dist: chromadb<2.0.0,>=1.1.0
Requires-Dist: gradio<6.0.0,>=5.49.0
Requires-Dist: langchain<0.4.0,>=0.3.27
Requires-Dist: langchain-chroma<0.3.0,>=0.2.6
Requires-Dist: langchain-community<0.4.0,>=0.3.30
Requires-Dist: langchain-core<0.4.0,>=0.3.78
Requires-Dist: langchain-google-genai<3.0.0,>=2.1.12
Requires-Dist: langchain-ollama<0.4.0,>=0.3.10
Requires-Dist: PyYAML<7.0.0,>=6.0.3
Requires-Dist: rapidfuzz<4.0.0,>=3.14.1
Requires-Dist: selenium<5.0.0,>=4.36.0
Requires-Dist: selenium-stealth<2.0.0,>=1.0.6
Requires-Dist: tqdm<5.0.0,>=4.67.1
Requires-Dist: webdriver-manager<5.0.0,>=4.0.2
Dynamic: author
Dynamic: home-page
Dynamic: license-file
Dynamic: requires-python
